{"ADMIN": {"username": "ADMIN", "password": "aaa", "banned": false, "restrictions": {"lower_letters": true, "upper_letters": false, "digits": false, "special": false}}, "grecha": {"username": "grecha", "password": "daniil", "banned": false, "restrictions": {"lower_letters": true, "upper_letters": true, "digits": true, "special": true}}, "rude": {"username": "rude", "password": "", "banned": true, "restrictions": {"lower_letters": false, "upper_letters": false, "digits": false, "special": false}}, "android 17": {"username": "android 17", "password": "dddd", "banned": false, "restrictions": {"lower_letters": true, "upper_letters": false, "digits": true, "special": true}}, "monmoseri": {"username": "monmoseri", "password": "1aW@23", "banned": false, "restrictions": {"lower_letters": true, "upper_letters": true, "digits": true, "special": true}}, "harrison": {"username": "harrison", "password": "!123As", "banned": false, "restrictions": {"lower_letters": true, "upper_letters": true, "digits": true, "special": true}}}